pyzod/__init__.py
pyzod/dataclass.py
pyzod/getters.py
pyzod/helpers.py
pyzod/types.py
pyzod/validators.py
pyzod-1.0.0.dist-info/METADATA
pyzod-1.0.0.dist-info/WHEEL
pyzod-1.0.0.dist-info/entry_points.txt
pyzod-1.0.0.dist-info/top_level.txt
pyzod-1.0.0.dist-info/RECORD
