Metadata-Version: 2.1
Name: pyzod
Version: 1.0.0
Summary: pyzod
Requires-Python: >=3.11
